AUTHORS
CHANGES
COPYING
INSTALL
MANIFEST.in
README
logfile.consent.dev.localhost
setup.cfg
setup.py
bin/consent-admin
bin/consent-makeconfig
bin/consent-test
src/consent/__init__.py
src/consent/accesscontrol.py
src/consent/application.py
src/consent/builder.py
src/consent/dictionary.py
src/consent/dictionarytest.py
src/consent/dictionarywords.py
src/consent/domtest.py
src/consent/exceptions.py
src/consent/filesystem.py
src/consent/filesystemtest.py
src/consent/handlerstest.py
src/consent/ioc.py
src/consent/kuitest.py
src/consent/migrate.py
src/consent/migratetest.py
src/consent/regexps.py
src/consent/registry.py
src/consent/soleInstance.py
src/consent/testrunner.py
src/consent/testunit.py
src/consent/unittesttest.py
src/consent/url.py
src/consent/urltest.py
src/consent/utilstest.py
src/consent.egg-info/PKG-INFO
src/consent.egg-info/SOURCES.txt
src/consent.egg-info/dependency_links.txt
src/consent.egg-info/not-zip-safe
src/consent.egg-info/requires.txt
src/consent.egg-info/top_level.txt
src/consent/cli/__init__.py
src/consent/cli/admin.py
src/consent/cli/admintest.py
src/consent/cli/data.py
src/consent/cli/makeconfig.py
src/consent/cli/test.py
src/consent/command/__init__.py
src/consent/command/emailjoinrequest.py
src/consent/command/initialise.py
src/consent/django/__init__.py
src/consent/django/apps/__init__.py
src/consent/django/apps/kui/__init__.py
src/consent/django/apps/kui/models/__init__.py
src/consent/django/apps/kui/models/kui.py
src/consent/django/apps/kui/urls/__init__.py
src/consent/django/apps/kui/urls/kui.py
src/consent/django/apps/kui/views/__init__.py
src/consent/django/apps/kui/views/accesscontrol.py
src/consent/django/apps/kui/views/admin.py
src/consent/django/apps/kui/views/api.py
src/consent/django/apps/kui/views/assembly.py
src/consent/django/apps/kui/views/base.py
src/consent/django/apps/kui/views/consensus.py
src/consent/django/apps/kui/views/kui.py
src/consent/django/apps/kui/views/manipulator.py
src/consent/django/apps/kui/views/member.py
src/consent/django/apps/kui/views/person.py
src/consent/django/apps/kui/views/proposal.py
src/consent/django/apps/kui/views/site.py
src/consent/django/apps/kui/views/testunit.py
