Metadata-Version: 1.0
Name: consent
Version: 0.6
Summary: Software for general assemblies
Home-page: http://pypi.python.org/pypi/consent
Author: Appropriate Software Foundation
Author-email: john.bywater@appropriatesoftware.net
License: AGPL
Platform: UNKNOWN
Classifier: Development Status :: 5 - Production/Stable
Classifier: Environment :: Console
Classifier: Environment :: Web Environment
Classifier: Intended Audience :: Developers
Classifier: License :: OSI Approved :: GNU Affero General Public License v3
Classifier: Operating System :: OS Independent
Classifier: Programming Language :: Python
Classifier: Topic :: Software Development :: Libraries :: Python Modules
